four_corner_method/__init__.py
four_corner_method/data/data.pkl
four_corner_method-0.2.0.dist-info/METADATA
four_corner_method-0.2.0.dist-info/WHEEL
four_corner_method-0.2.0.dist-info/licenses/LICENSE
four_corner_method-0.2.0.dist-info/RECORD
