Metadata-Version: 2.4
Name: four_corner_method
Version: 0.2.0
Summary: Four-corner method lookup for Chinese characters
Project-URL: Homepage, https://github.com/howl-anderson/four_corner_method
Project-URL: Repository, https://github.com/howl-anderson/four_corner_method
Author-email: Xiaoquan Kong <u1mail2me@gmail.com>
License-Expression: MIT
License-File: LICENSE
Requires-Python: >=3.10
Provides-Extra: dev
Requires-Dist: pytest; extra == 'dev'
